rdot/__init__.py
rdot/distortions.py
rdot/information.py
rdot/noise.py
rdot/postprocessing.py
rdot/probability.py
rdot/optimizers/__init__.py
rdot/optimizers/base.py
rdot/optimizers/ib.py
rdot/optimizers/ibmse.py
rdot/optimizers/rd.py
tests/__init__.py
tests/test_rd.py
rdot-0.0.28.dist-info/LICENSE
rdot-0.0.28.dist-info/METADATA
rdot-0.0.28.dist-info/WHEEL
rdot-0.0.28.dist-info/top_level.txt
rdot-0.0.28.dist-info/RECORD
